verysimplemodule/__init__.py
verysimplemodule/add.py
verysimplemodule/subtract.py
verysimplemodule/extras/__init__.py
verysimplemodule/extras/divide.py
verysimplemodule/extras/multiply.py
multiply_alexandre_1987-0.1.1.dist-info/METADATA
multiply_alexandre_1987-0.1.1.dist-info/WHEEL
multiply_alexandre_1987-0.1.1.dist-info/top_level.txt
multiply_alexandre_1987-0.1.1.dist-info/RECORD
