Metadata-Version: 2.4
Name: multiply-alexandre-1987
Version: 0.1.1
Summary: A very simple math module for demonstration
Author-email: Alexandre Vieira <sites.alexandre@gmail.com>
License: MIT
Project-URL: Homepage, https://github.com/yourusername/verysimplemodule
Project-URL: Bug Tracker, https://github.com/yourusername/verysimplemodule/issues
